regionx-0.2.0.dist-info/METADATA
regionx-0.2.0.dist-info/WHEEL
regionx-0.2.0.dist-info/licenses/LICENSE
regionx/__init__.py
regionx/regionx.cpython-313-darwin.so
regionx-0.2.0.dist-info/RECORD
