Metadata-Version: 2.4
Name: regionx
Version: 0.2.0
Classifier: Programming Language :: Rust
Classifier: Programming Language :: Python :: Implementation :: CPython
Classifier: Programming Language :: Python :: 3
Classifier: Programming Language :: Python :: 3 :: Only
Classifier: Operating System :: MacOS
Classifier: Operating System :: POSIX :: Linux
License-File: LICENSE
Summary: Fast region handling for catalogue data.
Author-email: Trystan Lambert <trystan.lambert@uwa.edu.au>
Requires-Python: >=3.12
